mergoo/compose_experts.py
mergoo/compose_layers.py
mergoo/safe_saving.py
mergoo/composers/__init__.py
mergoo/composers/composer_lora_moe.py
mergoo/composers/composer_moe.py
mergoo/models/__init__.py
mergoo/models/modeling_bert.py
mergoo/models/modeling_llama.py
mergoo/models/modeling_mistral.py
mergoo/models/modeling_phi3.py
mergoo-0.0.10.dist-info/LICENSE
mergoo-0.0.10.dist-info/METADATA
mergoo-0.0.10.dist-info/WHEEL
mergoo-0.0.10.dist-info/top_level.txt
mergoo-0.0.10.dist-info/RECORD
