Metadata-Version: 2.1
Name: mergoo
Version: 0.0.10
Summary: Impelementation of Leeroo LLM composer.
Author-email: Leeroo Team <support@leeroo.com>
License: GNU LESSER GENERAL PUBLIC LICENSE
Project-URL: homepage, https://github.com/Leeroo-AI/mergoo
Project-URL: repository, https://github.com/Leeroo-AI/mergoo
Keywords: LLM,compose,MoE,router,mixture-of-adapters,merge
License-File: LICENSE
Requires-Dist: torch >=2.0.0
Requires-Dist: tqdm ==4.66.2
Requires-Dist: safetensors ~=0.4.2
Requires-Dist: accelerate ~=0.27.2
Requires-Dist: transformers
Requires-Dist: huggingface-hub
Requires-Dist: peft
Requires-Dist: typing-extensions
Requires-Dist: sentencepiece
Requires-Dist: protobuf
Requires-Dist: numpy
Provides-Extra: dev
Requires-Dist: super-lint ; extra == 'dev'
